pymccorrelation/__init__.py
pymccorrelation/pymccorrelation.py
pymccorrelation-0.2.6.dist-info/LICENSE
pymccorrelation-0.2.6.dist-info/METADATA
pymccorrelation-0.2.6.dist-info/WHEEL
pymccorrelation-0.2.6.dist-info/top_level.txt
pymccorrelation-0.2.6.dist-info/RECORD
