Metadata-Version: 2.1
Name: pymccorrelation
Version: 0.2.6
Summary: Compute correlation coefficients with uncertainties
Home-page: https://github.com/privong/pymccorrelation
Author: George C. Privon
Author-email: gprivon@nrao.edu
Classifier: Development Status :: 4 - Beta
Classifier: License :: OSI Approved :: GNU General Public License v3 (GPLv3)
Classifier: Programming Language :: Python :: 3
Classifier: Operating System :: OS Independent
Classifier: Topic :: Scientific/Engineering
Requires-Python: >=3.6
License-File: LICENSE
Requires-Dist: numpy >=1.17
Requires-Dist: scipy
